aws_mfa_ks-0.0.14.data/scripts/aws-mfa
awsmfa/__init__.py
awsmfa/config.py
awsmfa/util.py
aws_mfa_ks-0.0.14.dist-info/LICENSE
aws_mfa_ks-0.0.14.dist-info/METADATA
aws_mfa_ks-0.0.14.dist-info/WHEEL
aws_mfa_ks-0.0.14.dist-info/entry_points.txt
aws_mfa_ks-0.0.14.dist-info/top_level.txt
aws_mfa_ks-0.0.14.dist-info/RECORD
