Metadata-Version: 2.1
Name: aws-mfa-ks
Version: 0.0.14
Summary: Manage AWS MFA Security Credentials
Home-page: https://github.com/ksylvan/aws-mfa
Author: Brian Nuszkowski
Author-email: brian@bnuz.co
License: MIT
License-File: LICENSE
Requires-Dist: boto3
